setup.cfg
setup.py
dexcell_api_v3.egg-info/PKG-INFO
dexcell_api_v3.egg-info/SOURCES.txt
dexcell_api_v3.egg-info/dependency_links.txt
dexcell_api_v3.egg-info/requires.txt
dexcell_api_v3.egg-info/top_level.txt
dexma_api_v3/__init__.py
dexma_api_v3/discovery.py
dexma_api_v3/factory/__init__.py
dexma_api_v3/factory/datasource.py
dexma_api_v3/factory/device.py
dexma_api_v3/factory/readings.py
dexma_api_v3/factory/reference_device.py
dexma_api_v3/factory/session.py
dexma_api_v3/factory/user.py
dexma_api_v3/factory/bases/__init__.py
dexma_api_v3/factory/bases/base_cost_concept.py
dexma_api_v3/factory/bases/base_entity.py
dexma_api_v3/factory/bases/base_entity_str.py
dexma_api_v3/factory/cost_electrical_factory/__init__.py
dexma_api_v3/factory/cost_electrical_factory/summary.py
dexma_api_v3/factory/cost_electrical_factory/consumption/__init__.py
dexma_api_v3/factory/cost_electrical_factory/consumption/tou.py
dexma_api_v3/factory/cost_electrical_factory/consumption/tou_wsn.py
dexma_api_v3/factory/cost_electrical_factory/demand/__init__.py
dexma_api_v3/factory/cost_electrical_factory/demand/multi_period.py
dexma_api_v3/factory/cost_electrical_factory/periods/__init__.py
dexma_api_v3/factory/cost_electrical_factory/periods/multiperiod_contracted_periods.py
dexma_api_v3/factory/cost_electrical_factory/periods/tou_periods.py
dexma_api_v3/factory/cost_electrical_factory/price_change/__init__.py
dexma_api_v3/factory/cost_electrical_factory/price_change/tou_change.py
dexma_api_v3/factory/cost_electrical_factory/values/__init__.py
dexma_api_v3/factory/cost_electrical_factory/values/tou_value.py
dexma_api_v3/factory/custom_types/__init__.py
dexma_api_v3/factory/custom_types/dateISO3601Type.py
dexma_api_v3/factory/custom_types/nullable_float_type.py
dexma_api_v3/factory/custom_types/nullable_string_type.py
dexma_api_v3/factory/custom_types/unsigned_float_type.py
dexma_api_v3/factory/custom_types/unsigned_long.py
dexma_api_v3/factory/location_factory/__init__.py
dexma_api_v3/factory/location_factory/branch.py
dexma_api_v3/factory/location_factory/leaf.py
dexma_api_v3/factory/location_factory/root.py
dexma_api_v3/factory/location_factory/section.py
