Metadata-Version: 1.1
Name: dexcell-api-v3
Version: 0.3.6
Summary: DEXCell Energy Manager HTTP/JSON REST API v3 for python
Home-page: https://bitbucket.org/dexmatech/dexcell_api_v3/
Author: David Cortes
Author-email: dcortes@dexmatetch.com
License: BSD
Platform: UNKNOWN
Classifier: Development Status :: 5 - Production/Stable
Classifier: Environment :: Web Environment
Classifier: Intended Audience :: Developers
Classifier: License :: OSI Approved :: BSD License
Classifier: Operating System :: OS Independent
Classifier: Programming Language :: Python
Classifier: Topic :: Software Development :: Libraries
Classifier: Topic :: Software Development :: Libraries :: Python Modules
Classifier: Topic :: Internet :: WWW/HTTP
Classifier: Programming Language :: Python :: 3
